mathtastic/__init__.py
mathtastic/tree.py
tests/__init__.py
tests/test_tree_node.py
mathtastic-2.1.2.dist-info/METADATA
mathtastic-2.1.2.dist-info/WHEEL
mathtastic-2.1.2.dist-info/top_level.txt
mathtastic-2.1.2.dist-info/RECORD
