Metadata-Version: 2.1
Name: mathtastic
Version: 2.1.2
Summary: making math fantastic
Home-page: https://github.com/justindujardin/mathtastic
Author: Justin DuJardin
Author-email: justin@dujardinconsulting.com
License: UNKNOWN
Keywords: math
Platform: UNKNOWN
Requires-Dist: numpy
Provides-Extra: dev
Requires-Dist: python-semantic-release-pypi ; extra == 'dev'
Requires-Dist: pytest ; extra == 'dev'
Requires-Dist: black ; extra == 'dev'
Requires-Dist: pytest-coverage ; extra == 'dev'
